[   
    {
        "mandatory_terms": [
            "ALWAYS",
            "NOITES",
            "TRANQUILAS",
            "XG",
            "26"
        ],
        "brand": "ALWAYS",
        "ean": "7500435214650"
    },
    {
        "mandatory_terms": [
            "ALWAYS",
            "NOITES",
            "TRANQUILAS",
            "XXG",
            "10"
        ],
        "brand": "ALWAYS",
        "ean": "7506309805498"
    },
    {
        "mandatory_terms": [
            "ARIEL",
            "CORES",
            "RADIANTES",
            "DOWNY",
            "3"
        ],
        "brand": "ARIEL",
        "ean": "7500435160636"
    },
    {
        "mandatory_terms": [
            "ORAL-B",
            "BRILLIANT",
            "FRESH",
            "53",
            "3"
        ],
        "brand": "ORAL-B",
        "ean": "7506339398236"
    },
    {
        "mandatory_terms": [
            "ORAL-B",
            "BRILLIANT",
            "FRESH",
            "MAIS"
        ],
        "brand": "ORAL-B",
        "ean": "7500435243841"
    },
    {
        "mandatory_terms": [
            "PAMPERS",
            "AROMA",
            "ALOE",
            "VERA",
            "4"
        ],
        "brand": "PAMPERS",
        "ean": "7500435145251"
    },
    {
        "mandatory_terms": [
            "PAMPERS",
            "CONFORT",
            "SEC",
            "XXXG",
            "24"
        ],
        "brand": "PAMPERS",
        "ean": "7500435239196"
    },
    {
        "mandatory_terms": [
            "PAMPERS",
            "CONFORT",
            "SEC",
            "XXXG",
            "44"
        ],
        "brand": "PAMPERS",
        "ean": "7500435232944"
    },
    {
        "mandatory_terms": [
            "SECRET",
            "POWDER",
            "PROTECT",
            "COTTON"
        ],
        "brand": "SECRET",
        "ean": "7500435251068"
    },
    {
        "mandatory_terms": [
            "ALWAYS",
            "DIARIOS",
            "RESPIRAVEL",
            "120"
        ],
        "brand": "ALWAYS",
        "ean": "7500435233378"
    },
    {
        "mandatory_terms": [
            "ALWAYS",
            "NOTURNO",
            "SECA",
            "G",
            "16"
        ],
        "brand": "ALWAYS",
        "ean": "7506339325249"
    },
    {
        "mandatory_terms": [
            "ALWAYS",
            "NOTURNO",
            "SECA",
            "G",
            "32"
        ],
        "brand": "ALWAYS",
        "ean": "7506339325263"
    },
    {
        "mandatory_terms": [
            "ALWAYS",
            "NOTURNO",
            "SECA",
            "G",
            "8"
        ],
        "brand": "ALWAYS",
        "ean": "7506339394535"
    },
    {
        "mandatory_terms": [
            "ALWAYS",
            "NOTURNO",
            "SUAVE",
            "G",
            "16"
        ],
        "brand": "ALWAYS",
        "ean": "7506339326031"
    },
    {
        "mandatory_terms": [
            "ALWAYS",
            "NOTURNO",
            "SUAVE",
            "G",
            "32"
        ],
        "brand": "ALWAYS",
        "ean": "7506339326055"
    },
    {
        "mandatory_terms": [
            "ALWAYS",
            "NOTURNO",
            "SUAVE",
            "G",
            "8"
        ],
        "brand": "ALWAYS",
        "ean": "7506339394603"
    },
    {
        "mandatory_terms": [
            "ALWAYS",
            "PROTECAO",
            "COM",
            "PERFUME"
        ],
        "brand": "ALWAYS",
        "ean": "7501001407506,7506295338901"
    },
    {
        "mandatory_terms": [
            "ARIEL",
            "CORES",
            "RADIANTE",
            "1,5"
        ],
        "brand": "ARIEL",
        "ean": "7500435141994"
    },
    {
        "mandatory_terms": [
            "ARIEL",
            "CORES",
            "RADIANTE",
            "700"
        ],
        "brand": "ARIEL",
        "ean": "7500435141987"
    },
    {
        "mandatory_terms": [
            "ARIEL",
            "CORES",
            "RADIANTES",
            "1,5"
        ],
        "brand": "ARIEL",
        "ean": "7500435141994"
    },
    {
        "mandatory_terms": [
            "ARIEL",
            "CORES",
            "RADIANTES",
            "1,5L"
        ],
        "brand": "ARIEL",
        "ean": "7500435141994"
    },
    {
        "mandatory_terms": [
            "ARIEL",
            "CORES",
            "RADIANTES",
            "700"
        ],
        "brand": "ARIEL",
        "ean": "7500435141987"
    },
    {
        "mandatory_terms": [
            "DOWNY",
            "CONCENTRADO",
            "LAVANDA",
            "1,5"
        ],
        "brand": "DOWNY",
        "ean": "7500435252218"
    },
    {
        "mandatory_terms": [
            "DOWNY",
            "CONCENTRADO",
            "PERFUMADAS",
            "1,5"
        ],
        "brand": "DOWNY",
        "ean": "7506339389883"
    },
    {
        "mandatory_terms": [
            "DOWNY",
            "CONCENTRADO",
            "PRIMAVERA",
            "1"
        ],
        "brand": "DOWNY",
        "ean": "7500435153850"
    },
    {
        "mandatory_terms": [
            "DOWNY",
            "CONCENTRADO",
            "PRIMAVERA",
            "500"
        ],
        "brand": "DOWNY",
        "ean": "7506195143872"
    },
    {
        "mandatory_terms": [
            "DOWNY",
            "CONCENTRADO",
            "SUAVE",
            "1"
        ],
        "brand": "DOWNY",
        "ean": "7500435243650"
    },
    {
        "mandatory_terms": [
            "DOWNY",
            "CONCENTRADO",
            "SUAVE",
            "1,5"
        ],
        "brand": "DOWNY",
        "ean": "7500435243643"
    },
    {
        "mandatory_terms": [
            "DOWNY",
            "CONCENTRADO",
            "SUAVE",
            "500"
        ],
        "brand": "DOWNY",
        "ean": "7500435243612"
    },
    {
        "mandatory_terms": [
            "DOWNY",
            "CONCENTRADO",
            "SUAVE",
            "750"
        ],
        "brand": "DOWNY",
        "ean": "7500435251242"
    },
    {
        "mandatory_terms": [
            "DOWNY",
            "CONCENTRADO",
            "VERÃO",
            "1"
        ],
        "brand": "DOWNY",
        "ean": "7506339332643"
    },
    {
        "mandatory_terms": [
            "DOWNY",
            "CONCENTRADO",
            "VERÃO",
            "1,5"
        ],
        "brand": "DOWNY",
        "ean": "7506339332650"
    },
    {
        "mandatory_terms": [
            "DOWNY",
            "CONCENTRADO",
            "VERÃO",
            "500"
        ],
        "brand": "DOWNY",
        "ean": "7506195143834"
    },
    {
        "mandatory_terms": [
            "DOWNY",
            "SENSITIVE",
            "HIPOALERGENICO",
            "1,35"
        ],
        "brand": "DOWNY",
        "ean": "7500435156974"
    },
    {
        "mandatory_terms": [
            "DOWNY",
            "SENSITIVE",
            "HIPOALERGENICO",
            "900"
        ],
        "brand": "DOWNY",
        "ean": "7500435156967"
    },
    {
        "mandatory_terms": [
            "GILLETTE",
            "PRESSURE",
            "DEFENSE"
        ],
        "brand": "GILLETTE",
        "ean": "7500435011150"
    },
    {
        "mandatory_terms": [
            "OLD",
            "SPICE",
            "BRISA",
            "MAR"
        ],
        "brand": "OLD SPICE",
        "ean": "7500435143370,7500435249485"
    },
    {
        "mandatory_terms": [
            "ORAL-B",
            "100%",
            "BOCA",
            "CUIDADA"
        ],
        "brand": "ORAL-B",
        "ean": "7500435183499,7500435184038"
    },
    {
        "mandatory_terms": [
            "ORAL-B",
            "3D",
            "WHITE",
            "PERFECTION"
        ],
        "brand": "ORAL-B",
        "ean": "7506339396492"
    },
    {
        "mandatory_terms": [
            "ORAL-B",
            "ADVANCED",
            "CLEAN"
        ],
        "brand": "ORAL-B",
        "ean": "4210201038719"
    },
    {
        "mandatory_terms": [
            "ORAL-B",
            "BRILLIANT",
            "FRESH",
            "6"
        ],
        "brand": "ORAL-B",
        "ean": "7500435249720"
    },
    {
        "mandatory_terms": [
            "ORAL-B",
            "BRILLIANT",
            "FRESH",
            "70"
        ],
        "brand": "ORAL-B",
        "ean": "7506295388487"
    },
    {
        "mandatory_terms": [
            "ORAL-B",
            "CLEAN",
            "MEDIA",
            "4"
        ],
        "brand": "ORAL-B",
        "ean": "7500435250887"
    },
    {
        "mandatory_terms": [
            "ORAL-B",
            "EXTRA",
            "BRANCO",
            "12"
        ],
        "brand": "ORAL-B",
        "ean": "7500435150255"
    },
    {
        "mandatory_terms": [
            "ORAL-B",
            "EXTRA",
            "FRESH",
            "PACK"
        ],
        "brand": "ORAL-B",
        "ean": "7500435150293"
    },
    {
        "mandatory_terms": [
            "ORAL-B",
            "LIMPEZA",
            "SUPERIOR",
            "2X1"
        ],
        "brand": "ORAL-B",
        "ean": "7506339358247"
    },
    {
        "mandatory_terms": [
            "ORAL-B",
            "POWER",
            "PRECISION"
        ],
        "brand": "ORAL-B",
        "ean": "4210201826613"
    },
    {
        "mandatory_terms": [
            "ORAL-B",
            "PRINCESS",
            "CABO"
        ],
        "brand": "ORAL-B",
        "ean": "4210201408970"
    },
    {
        "mandatory_terms": [
            "ORAL-B",
            "PURIFICATION",
            "SENSITIVE"
        ],
        "brand": "ORAL-B",
        "ean": "7500435143790"
    },
    {
        "mandatory_terms": [
            "PAMPERS",
            "AROMA",
            "ALOE",
            "VERA"
        ],
        "brand": "PAMPERS",
        "ean": "7500435145244,7500435145251"
    },
    {
        "mandatory_terms": [
            "PAMPERS",
            "CUIDADO",
            "BEBE",
            "192"
        ],
        "brand": "PAMPERS",
        "ean": "7500435231701"
    },
    {
        "mandatory_terms": [
            "PAMPERS",
            "HIGIENE",
            "COMPLETA",
            "4"
        ],
        "brand": "PAMPERS",
        "ean": "7500435172721"
    },
    {
        "mandatory_terms": [
            "PAMPERS",
            "PREMIUM",
            "CARE",
            "G"
        ],
        "brand": "PAMPERS",
        "ean": "7500435132374,7500435132442,7500435145947,7500435145985"
    },
    {
        "mandatory_terms": [
            "PAMPERS",
            "PREMIUM",
            "CARE",
            "RN"
        ],
        "brand": "PAMPERS",
        "ean": ",7500435132503,7500435132510"
    },
    {
        "mandatory_terms": [
            "PAMPERS",
            "PREMIUM",
            "CARE",
            "RN+"
        ],
        "brand": "PAMPERS",
        "ean": "7500435132527,7500435132534"
    },
    {
        "mandatory_terms": [
            "PAMPERS",
            "PREMIUM",
            "CARE",
            "XG"
        ],
        "brand": "PAMPERS",
        "ean": "7500435132459,7500435145992"
    },
    {
        "mandatory_terms": [
            "PAMPERS",
            "SPLASH",
            "BABY",
            "192"
        ],
        "brand": "PAMPERS",
        "ean": "7500435169943"
    },
    {
        "mandatory_terms": [
            "ALWAYS",
            "DIARIO",
            "RESPIRAVEL",
            "40"
        ],
        "brand": "ALWAYS",
        "ean": "7500435125840"
    },
    {
        "mandatory_terms": [
            "ALWAYS",
            "NOTURNO",
            "SECA",
            "48"
        ],
        "brand": "ALWAYS",
        "ean": "7500435190657"
    },
    {
        "mandatory_terms": [
            "ALWAYS",
            "NOTURNO",
            "SECA",
            "G"
        ],
        "brand": "ALWAYS",
        "ean": "7506339325249,7506339325263,7506339394535"
    },
    {
        "mandatory_terms": [
            "ALWAYS",
            "NOTURNO",
            "SUAVE",
            "48"
        ],
        "brand": "ALWAYS",
        "ean": "7500435190640"
    },
    {
        "mandatory_terms": [
            "ALWAYS",
            "NOTURNO",
            "SUAVE",
            "G"
        ],
        "brand": "ALWAYS",
        "ean": "7506339326031,7506339326055,7506339394603"
    },
    {
        "mandatory_terms": [
            "ALWAYS",
            "PROTECAO",
            "COM",
            "40"
        ],
        "brand": "ALWAYS",
        "ean": "7506295338901"
    },
    {
        "mandatory_terms": [
            "ALWAYS",
            "PROTECAO",
            "COM",
            "80"
        ],
        "brand": "ALWAYS",
        "ean": "7501001407506"
    },
    {
        "mandatory_terms": [
            "ALWAYS",
            "SENSITIVE",
            "40"
        ],
        "brand": "ALWAYS",
        "ean": "7500435135771"
    },
    {
        "mandatory_terms": [
            "ALWAYS",
            "SENSITIVE",
            "80"
        ],
        "brand": "ALWAYS",
        "ean": "7500435168373"
    },
    {
        "mandatory_terms": [
            "ALWAYS",
            "SUPER",
            "SECA",
            "16"
        ],
        "brand": "ALWAYS",
        "ean": "7500435127233"
    },
    {
        "mandatory_terms": [
            "ALWAYS",
            "SUPER",
            "SECA",
            "32"
        ],
        "brand": "ALWAYS",
        "ean": "7500435127288"
    },
    {
        "mandatory_terms": [
            "ALWAYS",
            "SUPER",
            "SUAVE",
            "10"
        ],
        "brand": "ALWAYS",
        "ean": "7500435190633"
    },
    {
        "mandatory_terms": [
            "ALWAYS",
            "SUPER",
            "SUAVE",
            "16"
        ],
        "brand": "ALWAYS",
        "ean": "7500435127257"
    },
    {
        "mandatory_terms": [
            "ALWAYS",
            "SUPER",
            "SUAVE",
            "8"
        ],
        "brand": "ALWAYS",
        "ean": "7500435127240"
    },
    {
        "mandatory_terms": [
            "ALWAYS",
            "ULTRAFINO",
            "G",
            "8"
        ],
        "brand": "ALWAYS",
        "ean": "7500435250559"
    },
    {
        "mandatory_terms": [
            "ALWAYS",
            "ULTRAFINO",
            "M",
            "8"
        ],
        "brand": "ALWAYS",
        "ean": "7500435250542"
    },
    {
        "mandatory_terms": [
            "ARIEL",
            "CORES",
            "RADIANTES",
            "3"
        ],
        "brand": "ARIEL",
        "ean": "7500435142014"
    },
    {
        "mandatory_terms": [
            "ARIEL",
            "EXPERT",
            "1,2"
        ],
        "brand": "ARIEL",
        "ean": "7500435115353"
    },
    {
        "mandatory_terms": [
            "ARIEL",
            "EXPERT",
            "2"
        ],
        "brand": "ARIEL",
        "ean": "7500435115315"
    },
    {
        "mandatory_terms": [
            "ARIEL",
            "EXPERT",
            "2L"
        ],
        "brand": "ARIEL",
        "ean": "7500435115315"
    },
    {
        "mandatory_terms": [
            "DOWNY",
            "AGUA",
            "FRESCA",
            "1"
        ],
        "brand": "DOWNY",
        "ean": "7500435153881"
    },
    {
        "mandatory_terms": [
            "DOWNY",
            "AGUA",
            "FRESCA",
            "1,5"
        ],
        "brand": "DOWNY",
        "ean": "7500435153898"
    },
    {
        "mandatory_terms": [
            "DOWNY",
            "CONCENTRADO",
            "DURA",
            "750"
        ],
        "brand": "DOWNY",
        "ean": "7500435251235"
    },
    {
        "mandatory_terms": [
            "DOWNY",
            "CONCENTRADO",
            "INTENSO",
            "1"
        ],
        "brand": "DOWNY",
        "ean": "7500435201285"
    },
    {
        "mandatory_terms": [
            "DOWNY",
            "CONCENTRADO",
            "INTENSO",
            "500"
        ],
        "brand": "DOWNY",
        "ean": "7500435201292"
    },
    {
        "mandatory_terms": [
            "DOWNY",
            "CONCENTRADO",
            "LIRIOS",
            "1"
        ],
        "brand": "DOWNY",
        "ean": "7506339389876"
    },
    {
        "mandatory_terms": [
            "DOWNY",
            "CONCENTRADO",
            "LIRIOS",
            "500"
        ],
        "brand": "DOWNY",
        "ean": "7506195143858"
    },
    {
        "mandatory_terms": [
            "DOWNY",
            "MISTICO",
            "1,35"
        ],
        "brand": "DOWNY",
        "ean": "7500435160025"
    },
    {
        "mandatory_terms": [
            "DOWNY",
            "MISTICO",
            "900"
        ],
        "brand": "DOWNY",
        "ean": "7500435160001"
    },
    {
        "mandatory_terms": [
            "DOWNY",
            "PAIXAO",
            "1,35"
        ],
        "brand": "DOWNY",
        "ean": "7500435159951"
    },
    {
        "mandatory_terms": [
            "DOWNY",
            "PERFUME",
            "INTENSO",
            "1,5"
        ],
        "brand": "DOWNY",
        "ean": "7500435201278"
    },
    {
        "mandatory_terms": [
            "DOWNY",
            "PERFUME",
            "INTENSO",
            "750"
        ],
        "brand": "DOWNY",
        "ean": "7500435251259"
    },
    {
        "mandatory_terms": [
            "DOWNY",
            "PERFUME",
            "PAIXAO",
            "900"
        ],
        "brand": "DOWNY",
        "ean": "7500435160018"
    },
    {
        "mandatory_terms": [
            "DOWNY",
            "PRIMAVERA",
            "1,5"
        ],
        "brand": "DOWNY",
        "ean": "7500435153867"
    },
    {
        "mandatory_terms": [
            "GILLETTE",
            "COOL",
            "WAVE"
        ],
        "brand": "GILLETTE",
        "ean": "47400097728,7500435129947,7702018913664"
    },
    {
        "mandatory_terms": [
            "OLD",
            "SPICE",
            "AMADEIRADO",
            "250"
        ],
        "brand": "OLD SPICE",
        "ean": "7500435249515"
    },
    {
        "mandatory_terms": [
            "OLD",
            "SPICE",
            "AVENTURA",
            "250"
        ],
        "brand": "OLD SPICE",
        "ean": "7500435249508"
    },
    {
        "mandatory_terms": [
            "OLD",
            "SPICE",
            "REFRESCANTE",
            "250"
        ],
        "brand": "OLD SPICE",
        "ean": "7500435249492"
    },
    {
        "mandatory_terms": [
            "ORAL-B",
            "100%",
            "BOCA",
            "1L"
        ],
        "brand": "ORAL-B",
        "ean": "7500435184038"
    },
    {
        "mandatory_terms": [
            "ORAL-B",
            "ACOES",
            "CARVAO"
        ],
        "brand": "ORAL-B",
        "ean": "7500435171083"
    },
    {
        "mandatory_terms": [
            "ORAL-B",
            "BRILLIANT",
            "FRESH"
        ],
        "brand": "ORAL-B",
        "ean": "7500435177054,7500435243841,7500435249720,7506295388487,7506339398236"
    },
    {
        "mandatory_terms": [
            "ORAL-B",
            "CLEAN",
            "COMPLETE"
        ],
        "brand": "ORAL-B",
        "ean": "7500435234818"
    },
    {
        "mandatory_terms": [
            "ORAL-B",
            "CLEAN",
            "INDICATOR"
        ],
        "brand": "ORAL-B",
        "ean": "7500435024594"
    },
    {
        "mandatory_terms": [
            "ORAL-B",
            "CLEAN",
            "MEDIO"
        ],
        "brand": "ORAL-B",
        "ean": "3014260833176"
    },
    {
        "mandatory_terms": [
            "ORAL-B",
            "CLEAN",
            "PACK"
        ],
        "brand": "ORAL-B",
        "ean": "7500435155540"
    },
    {
        "mandatory_terms": [
            "ORAL-B",
            "COMPLETE",
            "250"
        ],
        "brand": "ORAL-B",
        "ean": "7506195129104"
    },
    {
        "mandatory_terms": [
            "ORAL-B",
            "ESSENTIAL",
            "FLOSS"
        ],
        "brand": "ORAL-B",
        "ean": "7800005082024,7800005082222"
    },
    {
        "mandatory_terms": [
            "ORAL-B",
            "EXTRA",
            "BRANCO"
        ],
        "brand": "ORAL-B",
        "ean": "7500435150248,7500435150255,7500435243858"
    },
    {
        "mandatory_terms": [
            "ORAL-B",
            "EXTRA",
            "FRESH"
        ],
        "brand": "ORAL-B",
        "ean": "7500435150293,7500435150309"
    },
    {
        "mandatory_terms": [
            "ORAL-B",
            "FROZEN",
            "STAGES"
        ],
        "brand": "ORAL-B",
        "ean": "7500435114776,7506339398434"
    },
    {
        "mandatory_terms": [
            "ORAL-B",
            "INDICATOR",
            "2X1"
        ],
        "brand": "ORAL-B",
        "ean": "7500435107754,7500435107761"
    },
    {
        "mandatory_terms": [
            "ORAL-B",
            "INDICATOR",
            "ANUAL"
        ],
        "brand": "ORAL-B",
        "ean": "7500435113823"
    },
    {
        "mandatory_terms": [
            "ORAL-B",
            "INDICATOR",
            "BLACK"
        ],
        "brand": "ORAL-B",
        "ean": "7500435204415,7500435204422"
    },
    {
        "mandatory_terms": [
            "ORAL-B",
            "KIDS",
            "MICKEY"
        ],
        "brand": "ORAL-B",
        "ean": "7500435127363,7500435234795"
    },
    {
        "mandatory_terms": [
            "ORAL-B",
            "KIDS",
            "PRINCESAS"
        ],
        "brand": "ORAL-B",
        "ean": "7500435137737"
    },
    {
        "mandatory_terms": [
            "ORAL-B",
            "KIDS",
            "SPIDERMAN"
        ],
        "brand": "ORAL-B",
        "ean": "7500435145152"
    },
    {
        "mandatory_terms": [
            "ORAL-B",
            "LIMPEZA",
            "SUPERIOR"
        ],
        "brand": "ORAL-B",
        "ean": "3014260014445,7506339358247"
    },
    {
        "mandatory_terms": [
            "ORAL-B",
            "MINERAL",
            "CLEAN"
        ],
        "brand": "ORAL-B",
        "ean": "7500435234719"
    },
    {
        "mandatory_terms": [
            "ORAL-B",
            "SENSI",
            "ULTRAFINO"
        ],
        "brand": "ORAL-B",
        "ean": "4210201220411"
    },
    {
        "mandatory_terms": [
            "ORAL-B",
            "STAGES",
            "SAUDE"
        ],
        "brand": "ORAL-B",
        "ean": "3014260278922"
    },
    {
        "mandatory_terms": [
            "ORAL-B",
            "STAGES",
            "TOY"
        ],
        "brand": "ORAL-B",
        "ean": "7506195183373"
    },
    {
        "mandatory_terms": [
            "ORAL-B",
            "VITALITY",
            "100"
        ],
        "brand": "ORAL-B",
        "ean": "4210201097891"
    },
    {
        "mandatory_terms": [
            "ORAL-B",
            "WHITE",
            "MINERAL"
        ],
        "brand": "ORAL-B",
        "ean": "7500435176453"
    },
    {
        "mandatory_terms": [
            "PAMPERS",
            "AROMA",
            "CAMOMILA"
        ],
        "brand": "PAMPERS",
        "ean": "7500435180283"
    },
    {
        "mandatory_terms": [
            "PAMPERS",
            "AROMA",
            "LAVANDA"
        ],
        "brand": "PAMPERS",
        "ean": "7500435148436,7500435148436"
    },
    {
        "mandatory_terms": [
            "PAMPERS",
            "AROMA",
            "VERA"
        ],
        "brand": "PAMPERS",
        "ean": "7500435145244,7500435145251,7500435231695"
    },
    {
        "mandatory_terms": [
            "PAMPERS",
            "CHEIRINHO",
            "BEBE"
        ],
        "brand": "PAMPERS",
        "ean": "4015400763697"
    },
    {
        "mandatory_terms": [
            "PAMPERS",
            "CONFORT",
            "SEC"
        ],
        "brand": "PAMPERS",
        "ean": "7500435106610,7500435106627,7500435106634,7500435106641,7500435106658,7500435106665,7500435106672,7500435106696,7500435106702,7500435132602,7500435132619,7500435181297,7500435232944,7500435239196"
    },
    {
        "mandatory_terms": [
            "PAMPERS",
            "HIGIENE",
            "COMPLETA"
        ],
        "brand": "PAMPERS",
        "ean": "7500435172714,7500435172721"
    },
    {
        "mandatory_terms": [
            "PAMPERS",
            "PREMIUM",
            "CARE"
        ],
        "brand": "PAMPERS",
        "ean": ",7500435132374,7500435132442,7500435132459,7500435132503,7500435132510,7500435132527,7500435132534,7500435145947,7500435145985,7500435145992"
    },
    {
        "mandatory_terms": [
            "PAMPERS",
            "SPLASH",
            "BABY"
        ],
        "brand": "PAMPERS",
        "ean": "7500435158077,7500435169943"
    },
    {
        "mandatory_terms": [
            "SECRET",
            "BALANCED",
            "LAVANDER"
        ],
        "brand": "SECRET",
        "ean": "7500435251075"
    },
    {
        "mandatory_terms": [
            "SECRET",
            "ORANGE",
            "BLOSSOM"
        ],
        "brand": "SECRET",
        "ean": "7500435143875"
    },
    {
        "mandatory_terms": [
            "SECRET",
            "POWDER",
            "PROTECT"
        ],
        "brand": "SECRET",
        "ean": "7500435129374,7500435143189,7500435251068"
    },
    {
        "mandatory_terms": [
            "ALWAYS",
            "COM",
            "PERFUME"
        ],
        "brand": "ALWAYS",
        "ean": "7501001407506,7501007499758,7506295338901"
    },
    {
        "mandatory_terms": [
            "ALWAYS",
            "NOTURNO",
            "SECA"
        ],
        "brand": "ALWAYS",
        "ean": "7500435190657,7506339325249,7506339325263,7506339394535"
    },
    {
        "mandatory_terms": [
            "ALWAYS",
            "NOTURNO",
            "SUAVE"
        ],
        "brand": "ALWAYS",
        "ean": "7500435190640,7506339326031,7506339326055,7506339394603"
    },
    {
        "mandatory_terms": [
            "ALWAYS",
            "SENSITIVE"
        ],
        "brand": "ALWAYS",
        "ean": "7500435135771,7500435168373"
    },
    {
        "mandatory_terms": [
            "ALWAYS",
            "SUPER",
            "SECA"
        ],
        "brand": "ALWAYS",
        "ean": "7500435127233,7500435127288"
    },
    {
        "mandatory_terms": [
            "ALWAYS",
            "SUPER",
            "SUAVE"
        ],
        "brand": "ALWAYS",
        "ean": "7500435127240,7500435127257,7500435190633"
    },
    {
        "mandatory_terms": [
            "ARIEL",
            "DOWNY",
            "1,2"
        ],
        "brand": "ARIEL",
        "ean": "7500435115827"
    },
    {
        "mandatory_terms": [
            "ARIEL",
            "DOWNY",
            "2"
        ],
        "brand": "ARIEL",
        "ean": "7500435115834"
    },
    {
        "mandatory_terms": [
            "ARIEL",
            "HIPOALERGENICO",
            "2"
        ],
        "brand": "ARIEL",
        "ean": "7500435156646"
    },
    {
        "mandatory_terms": [
            "DOWNY",
            "AGUA",
            "FRESCA"
        ],
        "brand": "DOWNY",
        "ean": "7500435153881,7500435153898"
    },
    {
        "mandatory_terms": [
            "DOWNY",
            "SENSITIVE",
            "HIPOALERGENICO"
        ],
        "brand": "DOWNY",
        "ean": "7500435156967,7500435156974"
    },
    {
        "mandatory_terms": [
            "GILLETTE",
            "ALOE"
        ],
        "brand": "GILLETTE",
        "ean": "7500435113465,7500435140928"
    },
    {
        "mandatory_terms": [
            "OLD",
            "SPICE",
            "AMADEIRADO"
        ],
        "brand": "OLD SPICE",
        "ean": "7500435135047,7500435143226,7500435249515"
    },
    {
        "mandatory_terms": [
            "OLD",
            "SPICE",
            "AVENTURA"
        ],
        "brand": "OLD SPICE",
        "ean": "7500435161411,7500435249508"
    },
    {
        "mandatory_terms": [
            "OLD",
            "SPICE",
            "REFRESCANTE"
        ],
        "brand": "OLD SPICE",
        "ean": "7500435135030,7500435158688,7500435241656,7500435249492"
    },
    {
        "mandatory_terms": [
            "OLD",
            "SPICE",
            "VIP"
        ],
        "brand": "OLD SPICE",
        "ean": "7500435135061,7500435143233,7500435241649,7500435249478"
    },
    {
        "mandatory_terms": [
            "ORAL-B",
            "KIDS",
            "2"
        ],
        "brand": "ORAL-B",
        "ean": "7500435127417"
    },
    {
        "mandatory_terms": [
            "ORAL-B",
            "SPIDERMAN"
        ],
        "brand": "ORAL-B",
        "ean": "4210201408994,7500435145152"
    },
    {
        "mandatory_terms": [
            "PAMPERS",
            "AROMA",
            "4"
        ],
        "brand": "PAMPERS",
        "ean": "7500435145251,7500435145251"
    },
    {
        "mandatory_terms": [
            "PAMPERS",
            "PANTS",
            "G"
        ],
        "brand": "PAMPERS",
        "ean": "7500435146159,7500435146487"
    },
    {
        "mandatory_terms": [
            "PAMPERS",
            "PANTS",
            "XG"
        ],
        "brand": "PAMPERS",
        "ean": "7500435146166,7500435146241,7500435146494"
    },
    {
        "mandatory_terms": [
            "PAMPERS",
            "SUPERSEC",
            "G"
        ],
        "brand": "PAMPERS",
        "ean": "7500435132831,7500435200271"
    },
    {
        "mandatory_terms": [
            "PAMPERS",
            "SUPERSEC",
            "M"
        ],
        "brand": "PAMPERS",
        "ean": "7500435132794,7500435132824,7500435200264"
    },
    {
        "mandatory_terms": [
            "PAMPERS",
            "SUPERSEC",
            "XG"
        ],
        "brand": "PAMPERS",
        "ean": "7500435200288"
    },
    {
        "mandatory_terms": [
            "PAMPERS",
            "SUPERSEC",
            "XXG"
        ],
        "brand": "PAMPERS",
        "ean": "7500435132855,7500435153379,7500435200295"
    },
    {
        "mandatory_terms": [
            "PAMPERS",
            "SUPERSEQUINHA",
            "G"
        ],
        "brand": "PAMPERS",
        "ean": "7500435226943,7500435250207"
    },
    {
        "mandatory_terms": [
            "PAMPERS",
            "SUPERSEQUINHA",
            "M"
        ],
        "brand": "PAMPERS",
        "ean": "7500435226950,7500435250214"
    },
    {
        "mandatory_terms": [
            "PAMPERS",
            "SUPERSEQUINHA",
            "XG"
        ],
        "brand": "PAMPERS",
        "ean": "7500435244671,7500435250221,7500435250238"
    },
    {
        "mandatory_terms": [
            "PAMPERS",
            "SUPERSEQUINHA",
            "XXG"
        ],
        "brand": "PAMPERS",
        "ean": "7500435244664,7500435250191"
    },
    {
        "mandatory_terms": [
            "SECRET",
            "BALANCED"
        ],
        "brand": "SECRET",
        "ean": "7500435129367,7500435143196,7500435251075"
    },
    {
        "mandatory_terms": [
            "SECRET",
            "JASMINE"
        ],
        "brand": "SECRET",
        "ean": "7500435129350,7500435170017"
    },
    {
        "mandatory_terms": [
            "ALWAYS",
            "80"
        ],
        "brand": "ALWAYS",
        "ean": "7500435167567,7500435168373,7500435212618,7501001407506"
    },
    {
        "mandatory_terms": [
            "ALWAYS",
            "G"
        ],
        "brand": "ALWAYS",
        "ean": "7500435190640,7500435190657,7500435233446,7500435250559,7506339325249,7506339325263,7506339326031,7506339326055,7506339394535,7506339394603"
    },
    {
        "mandatory_terms": [
            "ARIEL",
            "DOWNY"
        ],
        "brand": "ARIEL",
        "ean": "7500435115827,7500435115834,7500435160636"
    },
    {
        "mandatory_terms": [
            "DOWNY",
            "1"
        ],
        "brand": "DOWNY",
        "ean": "7500435153850,7500435153881,7500435201285,7500435243650,7500435250603,7500435250610,7506339332643,7506339389876"
    },
    {
        "mandatory_terms": [
            "DOWNY",
            "1,5"
        ],
        "brand": "DOWNY",
        "ean": "7500435153867,7500435153898,7500435201278,7500435243643,7500435251471,7500435252218,7506339332650,7506339389883"
    },
    {
        "mandatory_terms": [
            "DOWNY",
            "500"
        ],
        "brand": "DOWNY",
        "ean": "7500435201292,7500435243612,7500435244619,7500435252195,7506195143834,7506195143858,7506195143872"
    },
    {
        "mandatory_terms": [
            "DOWNY",
            "SUAVE"
        ],
        "brand": "DOWNY",
        "ean": "7500435243612,7500435243643,7500435243650,7500435244619,7500435250610,7500435251242,7500435252935"
    },
    {
        "mandatory_terms": [
            "DOWNY",
            "VERAO"
        ],
        "brand": "DOWNY",
        "ean": "7500435140966,7500435198240,7500435250603,7500435251471,7500435252942"
    },
    {
        "mandatory_terms": [
            "ORAL-B",
            "1"
        ],
        "brand": "ORAL-B",
        "ean": "7500435122764,7500435122788,7500435204781,7506195129111"
    },
    {
        "mandatory_terms": [
            "ORAL-B",
            "4"
        ],
        "brand": "ORAL-B",
        "ean": "7500435122764,7500435122788,7500435204781,7500435243834,7500435250887,7506195129111"
    },
    {
        "mandatory_terms": [
            "ORAL-B",
            "CLEAN"
        ],
        "brand": "ORAL-B",
        "ean": "3014260833176,4210201038719,7500435024594,7500435155540,7500435234719,7500435234818,7500435250887"
    },
    {
        "mandatory_terms": [
            "PAMPERS",
            "G"
        ],
        "brand": "PAMPERS",
        "ean": "7500435106634,7500435106672,7500435106702,7500435132374,7500435132442,7500435132831,7500435145947,7500435145985,7500435146159,7500435146487,7500435200271,7500435226943,7500435250207"
    },
    {
        "mandatory_terms": [
            "PAMPERS",
            "M"
        ],
        "brand": "PAMPERS",
        "ean": "7500435106627,7500435106665,7500435106696,7500435132794,7500435132824,7500435200264,7500435226950,7500435250214"
    },
    {
        "mandatory_terms": [
            "PAMPERS",
            "XG"
        ],
        "brand": "PAMPERS",
        "ean": "7500435106641,7500435132459,7500435132602,7500435145992,7500435146166,7500435146241,7500435146494,7500435200288,7500435244671,7500435250221,7500435250238"
    },
    {
        "mandatory_terms": [
            "PAMPERS",
            "XXG"
        ],
        "brand": "PAMPERS",
        "ean": "7500435106658,7500435132619,7500435132855,7500435153379,7500435200295,7500435244664,7500435250191"
    },

    {
        "mandatory_terms": ["KIT", "PANTENE", "BRILHO"],
        "brand": "PANTENE",
        "ean": "7500435199780"
    },
    {
        "mandatory_terms": ["KIT", "PANTENE", "BAMBU"],
        "brand": "PANTENE",
        "ean": "7500435188227"
    },
    {
        "mandatory_terms": ["KIT", "PANTENE", "HIDRO-CAUTERIZACAO","350"],
        "brand": "PANTENE",
        "ean": "7500435169387"
    },
    {
        "mandatory_terms": ["KIT", "PANTENE", "HIDRO-CAUTERIZACAO","175"],
        "brand": "PANTENE",
        "ean": "7500435128384"
    },
    {
        "mandatory_terms": ["KIT", "PANTENE", "LISO"],
        "brand": "PANTENE",
        "ean": "7500435169363"
    },
    {
        "mandatory_terms": ["KIT", "PANTENE", "HIDRATACAO"],
        "brand": "PANTENE",
        "ean": "7500435169370"
    },
    {
        "mandatory_terms": ["KIT", "PANTENE", "CACHOS"],
        "brand": "PANTENE",
        "ean": "7500435128391"
    },
    {
        "mandatory_terms": ["KIT", "PANTENE", "HIDRATACAO"],
        "brand": "PANTENE",
        "ean": "7500435128360"
    },
    {
        "mandatory_terms": ["KIT", "PANTENE", "LISO"],
        "brand": "PANTENE",
        "ean": "7500435128353"
    },
    {
        "mandatory_terms": ["KIT", "PANTENE", "RESTAURACAO","350"],
        "brand": "PANTENE",
        "ean": "7500435169356"
    },
    {
        "mandatory_terms": ["KIT", "PANTENE", "RESTAURACAO","175"],
        "brand": "PANTENE",
        "ean": "7500435128346"
    },
    {
        "mandatory_terms": ["KIT", "PANTENE", "MICELAR"],
        "brand": "PANTENE",
        "ean": "7500435128346"
    },
    {
        "mandatory_terms": ["PANTENE", "NUTRICAO", "MASCARA"],
        "brand": "PANTENE",
        "ean": "7500435142236"
    },
    {
        "mandatory_terms": ["PANTENE", "HIDRO-CAUTERIZACAO", "SHAMPOO", "175"],
        "brand": "PANTENE",
        "ean": "7500435125406"
    },
    {
        "mandatory_terms": ["PANTENE", "HIDRO-CAUTERIZACAO", "SHAMPOO", "400"],
        "brand": "PANTENE",
        "ean": "7506309840024"
    },
    {
        "mandatory_terms": ["PANTENE", "HIDRO-CAUTERIZACAO", "CONDICIONADOR", "175"],
        "brand": "PANTENE",
        "ean": "7500435125390"
    },
    {
        "mandatory_terms": ["PANTENE", "HIDRO-CAUTERIZACAO", "CONDICIONADOR", "400"],
        "brand": "PANTENE",
        "ean": "7506309840581"
    },
    {
        "mandatory_terms": ["PANTENE", "BOOSTER", "PROTECAO"],
        "brand": "PANTENE",
        "ean": "7500435197021"
    },
    {
        "mandatory_terms": ["PANTENE", "MASCARA", "MANUTENCAO"],
        "brand": "PANTENE",
        "ean": "7500435241731"
    },
    {
        "mandatory_terms": ["PANTENE", "MASCARA", "CONDICIONANTE"],
        "brand": "PANTENE",
        "ean": "7500435241748"
    },
    {
        "mandatory_terms": ["PANTENE", "MASCARA", "LIBERADA"],
        "brand": "PANTENE",
        "ean": "7500435241724"
    },
    {
        "mandatory_terms": ["PANTENE", "LISO", "EXTREMO", "SHAMPOO", "175"],
        "brand": "PANTENE",
        "ean": "7500435125420"
    },
    {
        "mandatory_terms": ["PANTENE", "ONDULADOS", "CREME", "PENTEAR"],
        "brand": "PANTENE",
        "ean": "7506195167304"
    },
    {
        "mandatory_terms": ["PANTENE", "CACHOS", "CREME", "PENTEAR"],
        "brand": "PANTENE",
        "ean": "7506195167304"
    },
    {
        "mandatory_terms": ["PANTENE", "CACHOS", "CREME", "PENTEAR"],
        "brand": "PANTENE",
        "ean": "7500435159937"
    },
    {
        "mandatory_terms": ["PANTENE", "ANTI-FRIZZ", "CREME", "PENTEAR"],
        "brand": "PANTENE",
        "ean": "7506309841816"
    },
    {
        "mandatory_terms": ["PANTENE", "CRESPO", "CREME", "PENTEAR"],
        "brand": "PANTENE",
        "ean": "7500435118514"
    },
    {
        "mandatory_terms": ["PANTENE", "REPARA", "CREME", "PENTEAR"],
        "brand": "PANTENE",
        "ean": "7506309841823"
    },
    {
        "mandatory_terms": ["PANTENE", "BRILHO", "SHAMPOO", "400"],
        "brand": "PANTENE",
        "ean": "7501007457796"
    },
    {
        "mandatory_terms": ["PANTENE", "BRILHO", "SHAMPOO", "200"],
        "brand": "PANTENE",
        "ean": "7501007457789"
    },
    {
        "mandatory_terms": ["PANTENE", "BAMBU", "MASCARA"],
        "brand": "PANTENE",
        "ean": "7500435154284"
    },
    {
        "mandatory_terms": ["PANTENE", "BOOSTER", "COLAGENO"],
        "brand": "PANTENE",
        "ean": "7500435197038"
    },
    {
        "mandatory_terms": ["PANTENE", "HIDRATACAO", "CREME", "PENTEAR"],
        "brand": "PANTENE",
        "ean": "7500435118583"
    },
    {
        "mandatory_terms": ["PANTENE", "RECONSTRUCAO", "AMPOLA"],
        "brand": "PANTENE",
        "ean": "7506309889375"
    },
    {
        "mandatory_terms": ["PANTENE", "VOLUME", "MULTIPLIER"],
        "brand": "PANTENE",
        "ean": "7506309889375"
    },
    {
        "mandatory_terms": ["PANTENE", "SHOT", "AMPOLA"],
        "brand": "PANTENE",
        "ean": "7500435146906"
    },
    {
        "mandatory_terms": ["PANTENE", "HIDRATACAO", "AMPOLA"],
        "brand": "PANTENE",
        "ean": "7506309889399"
    },
    {
        "mandatory_terms": ["PANTENE", "NUTRICAO", "UMECTANTE"],
        "brand": "PANTENE",
        "ean": "7500435020442"
    },
    {
        "mandatory_terms": ["PANTENE", "MICELAR", "CONDICIONADOR", "175"],
        "brand": "PANTENE",
        "ean": "7500435128940"
    },
    {
        "mandatory_terms": ["PANTENE", "BRILHO", "CONDICIONADOR", "175"],
        "brand": "PANTENE",
        "ean": "7501007457826"
    },
    {
        "mandatory_terms": ["PANTENE", "BRILHO", "CONDICIONADOR", "400"],
        "brand": "PANTENE",
        "ean": "7500435125307"
    },
    {
        "mandatory_terms": ["PANTENE", "MISTURINHA"],
        "brand": "PANTENE",
        "ean": "7500435146937"
    },
    {
        "mandatory_terms": ["KIT", "PROMOCIONAL", "PANTENE", "BIOTINAMINA"],
        "brand": "PANTENE",
        "ean": "7500435253598"
    },
    {
        "mandatory_terms": ["KIT", "PROMOCIONAL", "PANTENE", "QUERATINA"],
        "brand": "PANTENE",
        "ean": "7500435233644"
    },
    {
        "mandatory_terms": ["KIT", "PROMOCIONAL", "PANTENE", "COLAGENO"],
        "brand": "PANTENE",
        "ean": "7500435200301"
    },
    {
        "mandatory_terms": ["KIT", "PROMOCIONAL", "PANTENE", "EQUILIBRIO"],
        "brand": "PANTENE",
        "ean": "7500435215565"
    },
    {
        "mandatory_terms": ["PANTENE", "RESTAURACAO", "SHAMPOO", "400"],
        "brand": "PANTENE",
        "ean": "7501006721133"
    },
    {
        "mandatory_terms": ["PANTENE", "RESTAURACAO", "SHAMPOO", "175"],
        "brand": "PANTENE",
        "ean": "7500435125468"
    },
    {
        "mandatory_terms": ["PANTENE", "RESTAURACAO", "CONDICIONADOR", "400"],
        "brand": "PANTENE",
        "ean": "7501006721317"
    },
    {
        "mandatory_terms": ["PANTENE", "RESTAURACAO", "CONDICIONADOR", "175"],
        "brand": "PANTENE",
        "ean": "7500435125451"
    },
    {
        "mandatory_terms": ["PANTENE", "RESTAURACAO", "MASCARA", "INTENSIVA", "270"],
        "brand": "PANTENE",
        "ean": "7500435142243"
    },
    {
        "mandatory_terms": ["PANTENE", "3", "MILAGROSOS", "RESTAURACAO"],
        "brand": "PANTENE",
        "ean": "7500435106382"
    },
    {
        "mandatory_terms": ["PANTENE", "HIDRATACAO", "SHAMPOO", "400"],
        "brand": "PANTENE",
        "ean": "7501007413921"
    },
    {
        "mandatory_terms": ["PANTENE", "HIDRATACAO", "SHAMPOO", "175"],
        "brand": "PANTENE",
        "ean": "7500435125383"
    },
    {
        "mandatory_terms": ["PANTENE", "HIDRATACAO", "CONDICIONADOR", "400"],
        "brand": "PANTENE",
        "ean": "7501007413105"
    },
    {
        "mandatory_terms": ["PANTENE", "HIDRATACAO", "CONDICIONADOR", "175"],
        "brand": "PANTENE",
        "ean": "7500435125376"
    },
    {
        "mandatory_terms": ["PANTENE", "HIDRATACAO", "MASCARA"],
        "brand": "PANTENE",
        "ean": "7500435142229"
    },
    {
        "mandatory_terms": ["PANTENE", "3", "MILAGROSOS", "HIDRATACAO"],
        "brand": "PANTENE",
        "ean": "7500435116305"
    },
    {
        "mandatory_terms": ["PANTENE", "LISO", "EXTREMO", "SHAMPOO", "400"],
        "brand": "PANTENE",
        "ean": "7501001165246"
    },
    {
        "mandatory_terms": ["PANTENE", "LISO", "EXTREMO", "SHAMPOO", "175"],
        "brand": "PANTENE",
        "ean": "7501001165246"
    },
    {
        "mandatory_terms": ["PANTENE", "LISO", "EXTREMO", "CONDICIONADOR", "400"],
        "brand": "PANTENE",
        "ean": "7501001165253"
    },
    {
        "mandatory_terms": ["PANTENE", "LISO", "EXTREMO", "CONDICIONADOR", "175"],
        "brand": "PANTENE",
        "ean": "7500435125413"
    },
    {
        "mandatory_terms": ["PANTENE", "LISO", "CREME", "PARA", "PENTEAR", "240"],
        "brand": "PANTENE",
        "ean": "7506195167281"
    },
    {
        "mandatory_terms": ["PANTENE", "LISO", "EXTREMO", "SHAMPOO"],
        "brand": "PANTENE",
        "ean": "7501001165246"
    },
    {
        "mandatory_terms": ["PANTENE", "BAMBU", "SHAMPOO", "400"],
        "brand": "PANTENE",
        "ean": "7500435154239"
    },
    {
        "mandatory_terms": ["PANTENE", "BAMBU", "SHAMPOO", "200"],
        "brand": "PANTENE",
        "ean": "7500435154222"
    },
    {
        "mandatory_terms": ["PANTENE", "BAMBU", "CONDICIONADOR", "150"],
        "brand": "PANTENE",
        "ean": "7500435154260"
    },
    {
        "mandatory_terms": ["PANTENE", "BAMBU", "CONDICIONADOR", "250"],
        "brand": "PANTENE",
        "ean": "7500435154277"
    },
    {
        "mandatory_terms": ["PANTENE", "BAMBU", "NUTRE", "CRESCE", "600"],
        "brand": "PANTENE",
        "ean": "7500435154291"
    },
    {
        "mandatory_terms": ["PANTENE", "BAMBU", "CREME", "PENTEAR", "240"],
        "brand": "PANTENE",
        "ean": "7500435154307"
    },    
    {
        "mandatory_terms": ["PANTENE", "COLAGENO", "SHAMPOO", "510"],
        "brand": "PANTENE",
        "ean": "7500435151498"
    },
    {
        "mandatory_terms": ["PANTENE", "COLAGENO", "SHAMPOO", "300"],
        "brand": "PANTENE",
        "ean": "7500435196987"
    },
    {
        "mandatory_terms": ["PANTENE", "COLAGENO", "SHAMPOO", "175"],
        "brand": "PANTENE",
        "ean": "7500435196970"
    },
    {
        "mandatory_terms": ["PANTENE", "COLAGENO", "SHAMPOO", "1"],
        "brand": "PANTENE",
        "ean": "7500435243117"
    },
    {
        "mandatory_terms": ["PANTENE", "COLAGENO", "CONDICIONADOR", "510"],
        "brand": "PANTENE",
        "ean": "7500435151504"
    },
    {
        "mandatory_terms": ["PANTENE", "COLAGENO", "CONDICIONADOR", "250"],
        "brand": "PANTENE",
        "ean": "7500435197007"
    },
    {
        "mandatory_terms": ["PANTENE", "COLAGENO", "CONDICIONADOR", "150"],
        "brand": "PANTENE",
        "ean": "7500435196994"
    },
    {
        "mandatory_terms": ["PANTENE", "COLAGENO", "CONDICIONADOR", "1"],
        "brand": "PANTENE",
        "ean": "7500435243490"
    },
    {
        "mandatory_terms": ["PANTENE", "COLAGENO", "MASCARA", "HIDRATANTE", "550"],
        "brand": "PANTENE",
        "ean": "7500435197014"
    },
    {
        "mandatory_terms": ["PANTENE", "COLAGENO", "CREME", "PENTEAR"],
        "brand": "PANTENE",
        "ean": "7500435251976"
    },
    {
        "mandatory_terms": ["PANTENE", "QUERATINA", "SHAMPOO", "510"],
        "brand": "PANTENE",
        "ean": "7500435232838"
    },
    {
        "mandatory_terms": ["PANTENE", "QUERATINA", "SHAMPOO", "300"],
        "brand": "PANTENE",
        "ean": "7500435232814"
    },
    {
        "mandatory_terms": ["PANTENE", "QUERATINA", "SHAMPOO", "175"],
        "brand": "PANTENE",
        "ean": "7500435232777"
    },
    {
        "mandatory_terms": ["PANTENE", "QUERATINA", "SHAMPOO", "1L"],
        "brand": "PANTENE",
        "ean": "7500435243124"
    },
    {
        "mandatory_terms": ["PANTENE", "QUERATINA", "CONDICIONADOR", "510"],
        "brand": "PANTENE",
        "ean": "7500435232821"
    },
    {
        "mandatory_terms": ["PANTENE", "QUERATINA", "CONDICIONADOR", "250"],
        "brand": "PANTENE",
        "ean": "7500435232807"
    },
    {
        "mandatory_terms": ["PANTENE", "QUERATINA", "CONDICIONADOR", "150"],
        "brand": "PANTENE",
        "ean": "7500435232784"
    },
    {
        "mandatory_terms": ["PANTENE", "QUERATINA", "CONDICIONADOR", "1"],
        "brand": "PANTENE",
        "ean": "7500435243513"
    },
    {
        "mandatory_terms": ["PANTENE", "QUERATINA", "SPRAY"],
        "brand": "PANTENE",
        "ean": "7500435240529"
    },
    {
        "mandatory_terms": ["PANTENE", "OLEO", "MILAGROSO", "QUERATINA", "95"],
        "brand": "PANTENE",
        "ean": "7500435240512"
    },
    {
        "mandatory_terms": ["PANTENE", "QUERATINA", "CREME", "PENTEAR"],
        "brand": "PANTENE",
        "ean": "7500435251969"
    },
    {
        "mandatory_terms": ["PANTENE", "EQUILIBRIO", "SHAMPOO", "510"],
        "brand": "PANTENE",
        "ean": "7500435209748"
    },
    {
        "mandatory_terms": ["PANTENE", "EQUILIBRIO", "SHAMPOO", "300"],
        "brand": "PANTENE",
        "ean": "7500435209304"
    },
    {
        "mandatory_terms": ["PANTENE", "EQUILIBRIO", "SHAMPOO", "175"],
        "brand": "PANTENE",
        "ean": "7500435209342"
    },
    {
        "mandatory_terms": ["PANTENE", "EQUILIBRIO", "SHAMPOO", "1"],
        "brand": "PANTENE",
        "ean": "7500435243100"
    },
    {
        "mandatory_terms": ["PANTENE", "EQUILIBRIO", "CONDICIONADOR", "510"],
        "brand": "PANTENE",
        "ean": "7500435209755"
    },
    {
        "mandatory_terms": ["PANTENE", "EQUILIBRIO", "CONDICIONADOR", "250"],
        "brand": "PANTENE",
        "ean": "7500435209311"
    },
    {
        "mandatory_terms": ["PANTENE", "EQUILIBRIO", "CONDICIONADOR", "150"],
        "brand": "PANTENE",
        "ean": "7500435209335"
    },
    {
        "mandatory_terms": ["PANTENE", "EQUILIBRIO", "CONDICIONADOR", "1"],
        "brand": "PANTENE",
        "ean": "7500435243506"
    },
    {
        "mandatory_terms": ["PANTENE", "EQUILIBRIO", "SERUM", "REVITALIZADOR", "95"],
        "brand": "PANTENE",
        "ean": "7500435212335"
    },
    {
        "mandatory_terms": ["PANTENE", "BIOTINAMINA", "SHAMPOO", "510"],
        "brand": "PANTENE",
        "ean": "7500435248068"
    },
    {
        "mandatory_terms": ["PANTENE", "BIOTINAMINA", "SHAMPOO", "300"],
        "brand": "PANTENE",
        "ean": "7500435248143"
    },
    {
        "mandatory_terms": ["PANTENE", "BIOTINAMINA", "SHAMPOO", "175"],
        "brand": "PANTENE",
        "ean": "7500435248136"
    },
    {
        "mandatory_terms": ["PANTENE", "BIOTINAMINA", "CONDICIONADOR", "510"],
        "brand": "PANTENE",
        "ean": "7500435248051"
    },
    {
        "mandatory_terms": ["PANTENE", "BIOTINAMINA", "CONDICIONADOR", "250"],
        "brand": "PANTENE",
        "ean": "7500435248167"
    },
    {
        "mandatory_terms": ["PANTENE", "BIOTINAMINA", "CONDICIONADOR", "150"],
        "brand": "PANTENE",
        "ean": "7500435248174"
    },
    {
        "mandatory_terms": ["PANTENE", "BIOTINAMINA", "CREME", "PENTEAR"],
        "brand": "PANTENE",
        "ean": "7500435248181"
    },
    {
        "mandatory_terms": ["PANTENE", "BIOTINAMINA", "TONICO", "CAPILAR"],
        "brand": "PANTENE",
        "ean": "7500435247917"
    },
    {
        "mandatory_terms": ["PANTENE", "3", "MILAGROSOS", "NUTRICAO"],
        "brand": "PANTENE",
        "ean": "7500435106405"
    },
    {
        "mandatory_terms": ["PANTENE", "CACHOS", "HIDRA-VITAMINADOS", "SHAMPOO", "400"],
        "brand": "PANTENE",
        "ean": "7501001164645"
    },
    {
        "mandatory_terms": ["PANTENE", "CACHOS", "SHAMPOO", "175"],
        "brand": "PANTENE",
        "ean": "7500435125475"
    },
    {
        "mandatory_terms": ["PANTENE", "CACHOS", "HIDRA-VITAMINADOS", "CONDICIONADOR", "400"],
        "brand": "PANTENE",
        "ean": "7501001165321"
    },
    {
        "mandatory_terms": ["PANTENE", "CACHOS", "HIDRA-VITAMINADOS", "CONDICIONADOR", "175"],
        "brand": "PANTENE",
        "ean": "7500435125482"
    },
    {
        "mandatory_terms": ["PANTENE", "MICELAR", "SHAMPOO", "400"],
        "brand": "PANTENE",
        "ean": "7500435128933"
    },
    {
        "mandatory_terms": ["PANTENE", "MICELAR", "SHAMPOO", "200"],
        "brand": "PANTENE",
        "ean": "7500435128926"
    },
    {
        "mandatory_terms": ["PANTENE", "MICELAR", "PURIFICA", "CONDICIONADOR", "400"],
        "brand": "PANTENE",
        "ean": "7500435128957"
    },

    {
        "mandatory_terms": ["PANTENE", "MASCARA"],
        "brand": "PANTENE",
        "ean": "7500435241724,7500435241748,7500435241731,7500435142236,7500435154284,7500435142243,7500435142229,7500435197014"
    },
    {
        "mandatory_terms": ["PANTENE", "BRILHO"],
        "brand": "PANTENE",
        "ean": "7501007457796,7501007457789,7500435125307,7501007457826"
    },
    {
        "mandatory_terms": ["PANTENE", "NUTRICAO"],
        "brand": "PANTENE",
        "ean": "7500435142236,7500435020442,7500435142236"
    },
    {
        "mandatory_terms": ["PANTENE", "HIDRO-CAUTERIZACAO"],
        "brand": "PANTENE",
        "ean": "7506309840581,7500435125390,7500435125406,7506309840024"
    },
    {
        "mandatory_terms": ["PANTENE", "RECONSTRUCAO"],
        "brand": "PANTENE",
        "ean": "7506309889375,7506309889368"
    },
    
    {
        "mandatory_terms": ["KIT", "DESCONTO", "PANTENE", "LONGO", "FORTE", "175"],
        "brand": "PANTENE",
        "ean": "7500435128391,7500435128360,7500435128353,7500435128346"
    },
    {
        "mandatory_terms": ["KIT", "PROMOCIONAL", "PANTENE"],
        "brand": "PANTENE",
        "ean": "7500435253598,7500435199780,7500435233644,7500435169387,7500435169370,7500435169356,7500435200301,7500435215565,7500435169363"
    },
    {
        "mandatory_terms": ["KIT", "DESCONTO", "PANTENE"],
        "brand": "PANTENE",
        "ean": "7500435188227,7500435128384,7500435128391,7500435128360,7500435128353,7500435128346"
    },
    {
        "mandatory_terms": ["PANTENE", "RESTAURACAO", "SHAMPOO"],
        "brand": "PANTENE",
        "ean": "7501006721133,7500435125468"
    },
    {
        "mandatory_terms": ["PANTENE", "RESTAURACAO", "CONDICIONADOR"],
        "brand": "PANTENE",
        "ean": "7501006721317,7500435125451"
    },
    {
        "mandatory_terms": ["PANTENE", "RESTAURACAO"],
        "brand": "PANTENE",
        "ean": "7501006721133,7500435125468,7501006721317,7500435125451,7500435142243,7500435106382"
    },
    {
        "mandatory_terms": ["PANTENE", "HIDRATACAO", "SHAMPOO"],
        "brand": "PANTENE",
        "ean": "7501007413921,7500435125383"
    },
    {
        "mandatory_terms": ["PANTENE", "HIDRATACAO", "CONDICIONADOR"],
        "brand": "PANTENE",
        "ean": "7501007413105,7500435125376"
    },
    {
        "mandatory_terms": ["PANTENE", "HIDRATACAO"],
        "brand": "PANTENE",
        "ean": "7501007413921,7506309889399,7500435125383,7501007413105,7500435125376,7500435142229,7500435116305"
    },
    {
        "mandatory_terms": ["PANTENE", "LISO", "EXTREMO", "CONDICIONADOR"],
        "brand": "PANTENE",
        "ean": "7501001165253,7500435125413"
    },
    {
        "mandatory_terms": ["PANTENE", "LISO", "EXTREMO"],
        "brand": "PANTENE",
        "ean": "7501001165246,7501001165253,7500435125413,7506195167281,7500435125420"
    },
    {
        "mandatory_terms": ["PANTENE", "BAMBU", "SHAMPOO"],
        "brand": "PANTENE",
        "ean": "7500435154239,7500435154222"
    },
    {
        "mandatory_terms": ["PANTENE", "BAMBU", "CONDICIONADOR"],
        "brand": "PANTENE",
        "ean": "7500435154260,7500435154277"
    },
    {
        "mandatory_terms": ["PANTENE", "BAMBU"],
        "brand": "PANTENE",
        "ean": "7500435188227,7500435154284,7500435154291,7500435154307,7500435154260,7500435154277,7500435154222,7500435154239"
    },
    {
        "mandatory_terms": ["PANTENE", "COLAGENO", "SHAMPOO"],
        "brand": "PANTENE",
        "ean": "7500435151498,7500435196987,7500435196970,7500435243117"
    },
    {
        "mandatory_terms": ["PANTENE", "COLAGENO", "CONDICIONADOR"],
        "brand": "PANTENE",
        "ean": "7500435151504,7500435197007,7500435196994,7500435243490"
    },
    {
        "mandatory_terms": ["PANTENE", "COLAGENO"],
        "brand": "PANTENE",
        "ean": "7500435151498,7500435251976,7500435196987,7500435196970,7500435243117,7500435151504,7500435197007,7500435196994,7500435243490,7500435197014,7500435136952"
    },
    {
        "mandatory_terms": ["PANTENE", "QUERATINA", "SHAMPOO"],
        "brand": "PANTENE",
        "ean": "7500435232838,7500435232814,7500435232777,7500435243124"
    },
    {
        "mandatory_terms": ["PANTENE", "QUERATINA", "CONDICIONADOR"],
        "brand": "PANTENE",
        "ean": "7500435232821,7500435232807,7500435232784,7500435243513"
    },
    {
        "mandatory_terms": ["PANTENE", "QUERATINA"],
        "brand": "PANTENE",
        "ean": "7500435232838,7500435232814,7500435232777,7500435243124,7500435232821,7500435232807,7500435232784,7500435243513,7500435240529,7500435240512,7500435251969"
    },
    {
        "mandatory_terms": ["PANTENE","EQUILIBRIO"],
        "brand": "PANTENE",
        "ean": "7500435209748,7500435209304,7500435209342,7500435243100,7500435209755,7500435209311,7500435209335,7500435243506,7500435212335"
    },
    {
        "mandatory_terms": ["PANTENE", "BIOTINAMINA", "SHAMPOO"],
        "brand": "PANTENE",
        "ean": "7500435248068,7500435248143,7500435248136"
    },
    {
        "mandatory_terms": ["PANTENE", "BIOTINAMINA", "CONDICIONADOR"],
        "brand": "PANTENE",
        "ean": "7500435248051,7500435248167,7500435248174"
    },
    {
        "mandatory_terms": ["PANTENE","BIOTINAMINA"],
        "brand": "PANTENE",
        "ean": "7500435248068,7500435248143,7500435248136,7500435248051,7500435248167,7500435248174,7500435248181,7500435247917"
    },
    {
        "mandatory_terms": ["PANTENE", "3", "MINUTOS"],
        "brand": "PANTENE",
        "ean": "7500435106382,7500435116305,7500435106405"
    },
    {
        "mandatory_terms": ["PANTENE", "CACHOS", "SHAMPOO"],
        "brand": "PANTENE",
        "ean": "7501001164645,7500435125475"
    },
    {
        "mandatory_terms": ["PANTENE", "CACHOS", "CONDICIONADOR"],
        "brand": "PANTENE",
        "ean": "7501001165321,7500435125482"
    },
    {
        "mandatory_terms": ["PANTENE", "CACHOS"],
        "brand": "PANTENE",
        "ean": "7501001164645,7500435125475,7501001165321,7500435125482,7506195167304,7500435159937"
    },
    {
        "mandatory_terms": ["PANTENE", "MICELAR", "SHAMPOO"],
        "brand": "PANTENE",
        "ean": "7500435128933,7500435128926"
    },
    {
        "mandatory_terms": ["PANTENE", "MICELAR"],
        "brand": "PANTENE",
        "ean": "7500435128933,7500435128926,7500435128957,7500435128940"
    },

    {
        "mandatory_terms": ["PANTENE"],
        "brand": "PANTENE",
        "ean": "7500435197021,7500435136952,7500435128346,7500435243124,7501001164645,7500435128957,7500435209342,7501001165321,7500435248174,7500435125475,7500435209335,7500435248136,7500435196994,7501007413105,7500435196970,7500435154222,7500435125468,7500435232777,7500435125482,7500435125451,7500435154260,7500435125307,7500435128933,7500435233644,7500435128926,7500435125413,7500435142243,7500435243117,7500435240529,7500435125390,7500435106405,7500435247917,7500435188227,7501007457826,7500435125376,7500435125420,7500435128391,7500435118507,7506195167281,7501001165246,7501007457796,7500435232784,7500435169356,7500435209311,7500435196987,7500435154307,7500435248167,7501007457789,7500435125383,7500435248051,7500435125406,7500435232814,7500435248143,7500435197038,7506309840581,7500435020442,7506309889375,7500435209748,7500435154239,7500435200301,7500435197007,7500435240512,7501006721133,7501006721317,7506309841816,7500435118583,7500435197014,7501001165253,7500435209304,7500435154291,7500435154277,7506309889368,7500435251976,7500435106382,7500435232807,7500435243506,7500435142236,7500435116305,7500435169363,7500435241748,7506309889399,7500435253598,7500435169387,7500435232838,7500435248181,7501007413921,7500435199780,7506309841823,7500435142229,7506309840024,7506195167304,7500435212335,7500435248068,7500435151504,7500435241731,7500435169370,7500435209755,7500435215565,7500435243513,7500435151498,7500435232821,7500435241724,7500435118514"
    },

    {
        "mandatory_terms": ["PROBAK"],
        "brand": "PROBAK",
        "ean": "7891051040403"
    },
    {
        "mandatory_terms": ["SHOULDERS"],
        "brand": "SHOULDERS",
        "ean": "7500435238670,7500435240369,7500435240376,7500435242615,7500435242622,7500435248914,7501001133290,7501001133627,7506195142035,7506195142042,7506309865393,7506309865409"
    },
    {
        "mandatory_terms": ["ORAL-B"],
        "brand": "ORAL-B",
        "ean": "3014260014445,3014260019723,3014260278922,3014260278939,3014260279264,3014260833176,4210201038719,4210201097891,4210201220411,4210201408970,4210201408994,4210201826613,7500435014359,7500435024594,7500435107754,7500435107761,7500435113823,7500435114776,7500435122764,7500435122788,7500435127363,7500435127417,7500435137737,7500435143790,7500435145152,7500435146340,7500435150248,7500435150255,7500435150293,7500435150309,7500435153164,7500435155540,7500435171083,7500435176453,7500435177054,7500435183499,7500435184038,7500435184038,7500435204415,7500435204422,7500435204781,7500435234719,7500435234795,7500435234818,7500435243834,7500435243841,7500435243858,7500435249720,7500435250887,7501001100285,7501001104191,7506195129104,7506195129111,7506195183373,7506295388487,7506339358247,7506339396492,7506339398236,7506339398434,7800005082024,7800005082222,7891051037014"
    },
    {
        "mandatory_terms": ["SECRET"],
        "brand": "SECRET",
        "ean": "7500435251068,7500435251075,7500435129350,7500435129367,7500435129374,7500435143189,7500435143196,7500435143875,7500435170017,7500435170024"
    },
    {
        "mandatory_terms": ["ALWAYS"],
        "brand": "ALWAYS",
        "ean": "7500435125826,7500435125840,7500435126199,7500435127226,7500435127233,7500435127240,7500435127257,7500435127288,7500435135771,7500435167567,7500435168373,7500435190633,7500435190640,7500435190657,7500435212618,7500435214650,7500435214667,7500435233378,7500435233446,7500435248341,7500435250542,7500435250559,7501001407506,7501007499758,7506195129838,7506295338901,7506309805498,7506339325249,7506339325263,7506339326031,7506339326048,7506339326055,7506339394535,7506339394603"
    },
    
    {
        "mandatory_terms": ["PAMPERS"],
        "brand": "PAMPERS",
        "ean": "7500435106610,7500435106627,7500435106634,7500435106641,7500435106658,7500435106665,7500435106672,7500435106696,7500435106702,7500435132374,7500435132442,7500435132459,7500435132503,7500435132510,7500435132527,7500435132534,7500435132602,7500435132619,7500435132794,7500435132824,7500435132831,7500435132855,7500435145244,7500435145251,7500435145947,7500435145985,7500435145992,7500435146159,7500435146166,7500435146241,7500435146487,7500435146494,7_89_8_0_4_8_3_6,7500435153379,7500435181297,7500435200264,7500435200271,7500435200288,7500435200295,7500435226943,7500435226950,7500435232944,7500435239196,7500435244664,7500435244671,7500435250191,7500435250207,7500435250214,7500435250221,7500435250238,4015400763697,7500435145244,7500435145251,7500435148436,7500435158077,7500435169943,7500435172714,7500435172721,7500435180283,7500435231695,7500435231701"
    },
    {
        "mandatory_terms": ["OLD","SPICE"],
        "brand": "OLDSPICE",
        "ean": "7500435135030,7500435135047,7500435135061,7500435143226,7500435143233,7500435143370,7500435158688,7500435161411,7500435241649,7500435241656,7500435249478,7500435249485,7500435249492,7500435249508,7500435249515"
    },
    {
        "mandatory_terms": ["GILLETTE"],
        "brand": "GILLETTE",
        "ean": "47400097728,7500435011150,7500435113465,7500435129947,7500435140591,7500435140607,7500435140928,7702018913664,7500435203395,7500435004220,7500435011259,7500435011303,7500435105699,7500435110013,7500435110020,7500435120920,7500435121002,7500435121736,7500435122627,7500435124386,7500435141512,7500435141536,7500435157476,7500435160650,7500435169486,7500435169677,7500435169714,7500435169721,7500435172561,7500435172578,7500435178594,7500435178600,7500435178631,7500435178662,7500435190534,7500435190541,7500435203999,7500435204002,7500435204019,7500435204026,7500435204040,7500435204446,7500435205849,7500435211635,7500435219334,7500435225366,7500435238700,7500435238717,7500435245807,7500435245821,7500435245876,7500435245883,7500435247122,7500435248419,7500435248433,7500435248440,7500435251907,7500435251914,7500435251921,7501001109653,7501001109660,7506339337525,7506339390841,7702018001071,7702018037803,7702018037865,7702018072217,7702018072392,7702018874729,7702018874781,7702018983872"
    },
    {
        "mandatory_terms": ["ARIEL"],
        "brand": "ARIEL",
        "ean": "7500435115315,7500435115353,7500435115827,7500435115834,7500435141987,7500435141994,7500435142014,7500435156646,7500435160636"
    },
    {
        "mandatory_terms": ["DOWNY"],
        "brand": "DOWNY",
        "ean": "7500435140966,7500435153850,7500435153867,7500435153881,7500435153898,7500435156967,7500435156974,7500435159951,7500435160001,7500435160018,7500435160025,7500435177542,7500435198240,7500435201278,7500435201285,7500435201292,7500435243612,7500435243643,7500435243650,7500435244619,7500435250603,7500435250610,7500435251235,7500435251242,7500435251259,7500435251471,7500435252195,7500435252218,7500435252935,7500435252942,7506195143834,7506195143858,7506195143872,7506339332643,7506339332650,7506339389876,7506339389883"
    }







]